rest_polymorphic/__init__.py
rest_polymorphic/__version__.py
rest_polymorphic/serializers.py
django_rest_polymorphic-0.1.10.dist-info/AUTHORS.rst
django_rest_polymorphic-0.1.10.dist-info/LICENSE
django_rest_polymorphic-0.1.10.dist-info/METADATA
django_rest_polymorphic-0.1.10.dist-info/WHEEL
django_rest_polymorphic-0.1.10.dist-info/top_level.txt
django_rest_polymorphic-0.1.10.dist-info/RECORD
