Metadata-Version: 1.1
Name: django-rest-polymorphic
Version: 0.1.10
Summary: Polymorphic serializers for Django REST Framework.
Home-page: https://github.com/denisorehovsky/django-rest-polymorphic
Author: Denis Orehovsky
Author-email: denis.orehovsky@gmail.com
License: MIT License
Platform: UNKNOWN
Classifier: License :: OSI Approved :: MIT License
Classifier: Intended Audience :: Developers
Classifier: Framework :: Django
Classifier: Framework :: Django :: 2.2
Classifier: Framework :: Django :: 3.0
Classifier: Programming Language :: Python
Classifier: Programming Language :: Python :: 3.6
Classifier: Programming Language :: Python :: 3.7
Classifier: Programming Language :: Python :: 3.8
Classifier: Programming Language :: Python :: Implementation :: CPython
Classifier: Programming Language :: Python :: Implementation :: PyPy
